alphacodings/__init__.py
alphacodings/base26.py
alphacodings/base52.py
alphacodings/common.py
alphacodings/py.typed
alphacodings-0.2.0.dist-info/METADATA
alphacodings-0.2.0.dist-info/WHEEL
alphacodings-0.2.0.dist-info/licenses/LICENSE
alphacodings-0.2.0.dist-info/RECORD
