Metadata-Version: 2.3
Name: alphacodings
Version: 0.2.0
Summary: base26 ([A-Z]) and base52 ([A-Za-z]) encodings
Author-email: Federico Minutoli <fede97.minutoli@gmail.com>
License: MIT License
Keywords: GMP,NLP,chunking,encodings,tokenization
Requires-Python: >3.9
Requires-Dist: gmpy2>1
